README.rst
setup.py
stringsheet/__init__.py
stringsheet/api.py
stringsheet/cli.py
stringsheet/comparator.py
stringsheet/constants.py
stringsheet/main.py
stringsheet/model.py
stringsheet/parser.py
stringsheet/writer.py
stringsheet.egg-info/PKG-INFO
stringsheet.egg-info/SOURCES.txt
stringsheet.egg-info/dependency_links.txt
stringsheet.egg-info/entry_points.txt
stringsheet.egg-info/requires.txt
stringsheet.egg-info/top_level.txt