Metadata-Version: 1.0
Name: stringsheet
Version: 0.2.3
Summary: Manage Android translations using Google Spreadsheets
Home-page: https://github.com/Tunous/StringsSheet
Author: Łukasz Rutkowski
Author-email: lukus178@gmail.com
License: MIT
Platform: UNKNOWN
